{"default-sidebar":{"search-2":{"title":""},"text-1":{"title":"ABOUT SPYRO","text":"Spyro is a marketing landing page theme, that lets you build stunning high performance landing pages using a fully visual interface. Start with any of the demos below or build one on your own.\r\n\r\n[tatsu_button button_text= \"Get Started\" url= \"\" new_tab= \"0\" type= \"small\" button_style= \"rounded\" alignment= \"none\" bg_color= '{\"id\":\"palette:0\",\"color\":\"rgba(36,108,255,1)\"}' hover_bg_color= \"\" color= '{\"id\":\"palette:1\",\"color\":\"#ffffff\"}' hover_color= \"rgba(255,255,255,1)\" border_width= \"0\" border_color= \"\" hover_border_color= \"\" icon= \"\" icon_alignment= \"left\" lightbox= \"0\" image= \"\" video_url= \"\" hover_effect= \"button-transform\" background_animation= \"none\" margin= '{\"d\":\"\"}' box_shadow= \"0px 0px 0px 0px rgba(0,0,0,0)\" hover_box_shadow= \"0px 0px 0px 0px rgba(0,0,0,0)\" border_style= '{\"d\":\"solid\",\"l\":\"solid\",\"t\":\"solid\",\"m\":\"solid\"}' border= '{\"d\":\"0px 0px 0px 0px\"}' outer_border_color= \"\" hide_in= \"\" css_id= \"\" css_classes= \"spyro-get-started-button\" animate= \"1\" animation_type= \"none\" animation_delay= \"0\" animation_duration= \"300\" padding= '{\"d\":\"\"}' border_radius= \"\" key= \"S1E4LuFD_\"][\/tatsu_button]","filter":true,"visual":true},"be-recent-posts-1":{"title":"","number":3},"tag_cloud-2":{"title":"","count":0,"taxonomy":"post_tag"}},"footer-widget-1":{"be-recent-posts-2":{"title":" ","number":3}},"footer-widget-2":{"tag_cloud-1":{"title":"IMPORTANT LINKS :","count":0,"taxonomy":"post_tag"}}}